authorization_api/__init__.py
authorization_api/authorization_api.py
authorization_api/authorization_api.yaml
authorization_api/authorization_lambda.py
authorization_api/authorization_users.py
authorization_api/readme.md
authorization_api/validation_function.py
authorization_api/validator_lambda.py
authorization_api-0.7.0.dist-info/licenses/LICENSE
authorization_api-0.7.0.dist-info/WHEEL
authorization_api-0.7.0.dist-info/METADATA
authorization_api-0.7.0.dist-info/RECORD
