Metadata-Version: 2.4
Name: authorization-api
Version: 0.7.0
Summary: A Pulumi component for deploying a secure, fully managed AWS Cognito-backed authorization REST API with Lambda and API Gateway.
Author-email: Daniel Repik <danrepik@icloud.com>
Requires-Python: >=3.9
Classifier: Programming Language :: Python :: 3.9
Classifier: Operating System :: OS Independent
License-File: LICENSE
Requires-Dist: pulumi
Requires-Dist: pulumi-aws
Requires-Dist: boto3
Project-URL: Documentation, https://github.com/DanRepik/cloud-foundry
Project-URL: Source, https://github.com/DanRepik/cloud-foundry
